README.md
setup.py
GetConfigDictClass/GetConfigDictClass.py
GetConfigDictClass/__init__.py
GetConfigDictClass.egg-info/PKG-INFO
GetConfigDictClass.egg-info/SOURCES.txt
GetConfigDictClass.egg-info/dependency_links.txt
GetConfigDictClass.egg-info/top_level.txt